[
  {
    "document_number": "2007000731113",
    "grantors": "WELLS FARGO BK N A",
    "grantees": "U S BK N A TR",
    "grantor_grantees": "MASTRANGELO ANTHONY J",
    "document_type": "ASGT TRUST DEED",
    "recording_date": "12/12/2007",
    "pages": "1",
    "found_via_names": ["MASTRANGELO ANTHONY"],
    "relevance_note": "Name variant ANTHONY J — verify against subject property"
  },
  {
    "document_number": "2008000415094",
    "grantors": "WASHINGTON MUTL BK FA",
    "grantees": "LASALLE BK NA TR",
    "grantor_grantees": "MASTRANGELO ANTHONY J",
    "document_type": "ASGT TRUST DEED",
    "recording_date": "9/2/2008",
    "pages": "1",
    "found_via_names": ["MASTRANGELO ANTHONY"],
    "relevance_note": "Name variant ANTHONY J — verify against subject property"
  },
  {
    "document_number": "2017000154868",
    "grantors": "QUICKEN LOANS INC",
    "grantees": "CHARLES SCHWAB BANK",
    "grantor_grantees": "MASTRANGELO ANTHONY; MASTRANGELO GEORGIANN",
    "document_type": "ASGT TRUST DEED",
    "recording_date": "4/18/2017",
    "pages": "3",
    "found_via_names": ["MASTRANGELO ANTHONY", "MASTRANGELO GEORGIANN"]
  },
  {
    "document_number": "2021000182215",
    "grantors": "PICCIOTTA DANIELA",
    "grantees": "MASTRANGELO ANTHONY MICHAEL TR",
    "grantor_grantees": "",
    "document_type": "GRANT DEED",
    "recording_date": "3/16/2021",
    "pages": "2",
    "found_via_names": ["MASTRANGELO ANTHONY MICHAEL"],
    "relevance_note": "ACQUISITION — Property conveyed to Mastrangelo Trust"
  },
  {
    "document_number": "2021000182216",
    "grantors": "MASTRANGELO ANTHONY MICHAEL TR",
    "grantees": "EMPIRE OF AMERICA CORPORATION MORTGAGE ELECTRONIC REGISTRATION SYSTEMS INC",
    "grantor_grantees": "",
    "document_type": "TRUST DEED",
    "recording_date": "3/16/2021",
    "pages": "25",
    "found_via_names": ["MASTRANGELO ANTHONY MICHAEL"],
    "relevance_note": "PURCHASE MONEY MORTGAGE — Same day as Grant Deed"
  },
  {
    "document_number": "2021000188480",
    "grantors": "MASTRANGELO ANTHONY M MASTRANGELO GEORGIANN I",
    "grantees": "MASTRANGELO ANTHONY MICHAEL TR",
    "grantor_grantees": "",
    "document_type": "DEED",
    "recording_date": "3/18/2021",
    "pages": "2",
    "found_via_names": ["MASTRANGELO ANTHONY MICHAEL"],
    "relevance_note": "TRANSFER TO TRUST — Individual to Trustee"
  },
  {
    "document_number": "2021000188481",
    "grantors": "MASTRANGELO ANTHONY MASTRANGELO GEORGIANN",
    "grantees": "MASTRANGELO ANTHONY MICHAEL TR",
    "grantor_grantees": "",
    "document_type": "DEED",
    "recording_date": "3/18/2021",
    "pages": "2",
    "found_via_names": ["MASTRANGELO ANTHONY MICHAEL"],
    "relevance_note": "TRANSFER TO TRUST — Companion deed"
  },
  {
    "document_number": "2021000262319",
    "grantors": "MASTRANGELO ANTHONY MICHAEL TR",
    "grantees": "EMPIRE OF AMERICA CORPORATION MORTGAGE ELECTRONIC REGISTRATION SYSTEMS INC",
    "grantor_grantees": "",
    "document_type": "TRUST DEED",
    "recording_date": "4/19/2021",
    "pages": "22",
    "found_via_names": ["MASTRANGELO ANTHONY MICHAEL"],
    "relevance_note": "MORTGAGE — Possible refinance"
  },
  {
    "document_number": "2021000262325",
    "grantors": "MASTRANGELO ANTHONY MICHAEL TR",
    "grantees": "EMPIRE OF AMERICA CORPORATION MORTGAGE ELECTRONIC REGISTRATION SYSTEMS INC",
    "grantor_grantees": "",
    "document_type": "TRUST DEED",
    "recording_date": "4/19/2021",
    "pages": "26",
    "found_via_names": ["MASTRANGELO ANTHONY MICHAEL"],
    "relevance_note": "MORTGAGE — Second Trust Deed same day as 2021000262319"
  },
  {
    "document_number": "2023000027298",
    "grantors": "MASTRANGELO ANTHONY MICHAEL TR",
    "grantees": "FLAGSTAR BANK N A",
    "grantor_grantees": "",
    "document_type": "TRUST DEED",
    "recording_date": "2/8/2023",
    "pages": "21",
    "found_via_names": ["MASTRANGELO ANTHONY MICHAEL"],
    "relevance_note": "MORTGAGE — Flagstar Bank"
  },
  {
    "document_number": "2025000155224",
    "grantors": "MASTRANGELO FAMILY TRUST",
    "grantees": "MASTRANGELO ANTHONY MARIO COTR MASTRANGELO JO ANNE COTR",
    "grantor_grantees": "",
    "document_type": "AFFIDAVIT",
    "recording_date": "6/2/2025",
    "pages": "6",
    "found_via_names": ["MASTRANGELO FAMILY TRUST"],
    "relevance_note": "CAUTION — Co-Trustees are ANTHONY MARIO & JO ANNE (different from ANTHONY MICHAEL & GEORGIANN IRENE). Likely different trust."
  },
  {
    "document_number": "2026000034332",
    "grantors": "MASTRANGELO ANTHONY MICHAEL MASTRANGELO ANTHONY MICHAEL TR",
    "grantees": "PARTNERS FEDERAL CREDIT UNION",
    "grantor_grantees": "",
    "document_type": "TRUST DEED",
    "recording_date": "2/13/2026",
    "pages": "8",
    "found_via_names": ["MASTRANGELO ANTHONY MICHAEL"],
    "relevance_note": "MOST RECENT MORTGAGE — Individual AND Trustee capacity"
  },
  {
    "document_number": "2026000053382",
    "grantors": "",
    "grantees": "MASTRANGELO ANTHONY MICHAEL TR",
    "grantor_grantees": "",
    "document_type": "RECONVEYANCE",
    "recording_date": "2/23/2026",
    "pages": "1",
    "found_via_names": ["MASTRANGELO ANTHONY MICHAEL"],
    "relevance_note": "RELEASES prior Trust Deed — likely the Flagstar loan (2023000027298)"
  }
]
